{
  "$schema": "../gen/schemas/desktop-schema.json",
  "identifier": "desktop-capability",
  "platforms": ["linux", "macOS", "windows"],
  "windows": ["win_*"],
  "permissions": [
    "app:default",
    "path:default",
    "event:default",
    "resources:default",
    "image:default",
    "menu:default",
    "tray:default",
    "window:default",
    "window:allow-close",
    "window:allow-show",
    "window:allow-hide",
    "window:allow-set-always-on-top",
    "window:allow-start-dragging",
    "window:allow-set-decorations",
    "window:allow-minimize",
    "window:allow-maximize",
    "window:allow-toggle-maximize",
    "window:allow-set-shadow",
    "dialog:default",
    "dialog:allow-confirm",
    "dialog:allow-open",
    "fs:default",
    "shell:default",
    "shell:allow-open",
    "process:default",
    "process:allow-exit",
    "process:allow-restart",
    "updater:default",
    "clipboard-manager:default",
    "log:default",
    "window-state:default"
  ]
}
